<AVSImageRaw3EXIFGenerator ver="1">	<!-- A. Tags relating to image data structure -->	<ImageWidth					tagid="256"		tagname="Image width"									type="SHORT | LONG"		count="1"></ImageWidth>	<ImageLength				tagid="257"		tagname="Image height"									type="SHORT | LONG"		count="1"></ImageLength>	<BitsPerSample				tagid="258"		tagname="Number of bits per component"					type="SHORT"			count="3"></BitsPerSample>	<Compression				tagid="259"		tagname="Compression scheme"							type="SHORT"			count="1"></Compression>	<PhotometricInterpretation	tagid="262"		tagname="Pixel composition"								type="SHORT"			count="1"></PhotometricInterpretation>	<Orientation				tagid="274"		tagname="Orientation of image"							type="SHORT"			count="1"></Orientation>	<SamplesPerPixel			tagid="277"		tagname="Number of components"							type="SHORT"			count="1" ></SamplesPerPixel>	<PlanarConfiguration		tagid="284"		tagname="Image data arrangement"						type="SHORT"			count="1" ></PlanarConfiguration>	<YCbCrSubSampling			tagid="530"		tagname="Subsampling ratio of Y to C"					type="SHORT"			count="2" ></YCbCrSubSampling>	<YCbCrPositioning			tagid="531"		tagname="Y and C positioning"							type="SHORT"			count="1" ></YCbCrPositioning>	<XResolution				tagid="282"		tagname="Image resolution in width direction"			type="RATIONAL"			count="1" ></XResolution>	<YResolution				tagid="283"		tagname="Image resolution in height direction"			type="RATIONAL"			count="1" ></YResolution>	<ResolutionUnit				tagid="296"		tagname="Unit of X and Y resolution"					type="SHORT"			count="1" ></ResolutionUnit>	<!-- B. Tags relating to recording offset -->	<StripOffsets				tagid="273"		tagname="Image data location"							type="SHORT | LONG"		count="*S"></StripOffsets>	<RowsPerStrip				tagid="278"		tagname="Number of rows per strip"						type="SHORT | LONG"		count="1"></RowsPerStrip>	<StripByteCounts			tagid="279"		tagname="Bytes per compressed strip"					type="SHORT | LONG"		count="*S"></StripByteCounts>	<JPEGInterchangeFormat		tagid="513"		tagname="Offset to JPEG SOI"							type="LONG"				count="1"></JPEGInterchangeFormat>	<JPEGInterchangeFormatLength tagid="514"	tagname="Bytes of JPEG data"							type="LONG"				count="1"></JPEGInterchangeFormatLength>	<!-- C. Tags relating to image data characteristics -->	<TransferFunction			tagid="301"		tagname="Transfer function"								type="SHORT"			count="768"></TransferFunction>	<WhitePoint					tagid="318"		tagname="White point chromaticity"						type="RATIONAL"			count="2"></WhitePoint>	<PrimaryChromaticities		tagid="319"		tagname="Chromaticities of primaries"					type="RATIONAL"			count="6"></PrimaryChromaticities>	<YCbCrCoefficients			tagid="529"		tagname="Color space transformation matrix coefficients"	type="RATIONAL"		count="3"></YCbCrCoefficients>	<ReferenceBlackWhite		tagid="532"		tagname="Pair of black and white reference values"		type="RATIONAL"			count="6"></ReferenceBlackWhite>	<!-- D. Other tags -->	<DateTime					tagid="306"		tagname="File change date and time"						type="ASCII"			count="20"></DateTime>	<ImageDescription			tagid="270"		tagname="Image title"									type="ASCII"			count="Any"></ImageDescription>	<Make 						tagid="271"		tagname="Image input equipment manufacturer"			type="ASCII"			count="Any"></Make>	<Model						tagid="272"		tagname="Image input equipment model"					type="ASCII"			count="Any"></Model>	<Software					tagid="305"		tagname="Software used"									type="ASCII"			count="Any"></Software>	<Artist						tagid="315"		tagname="Person who created the image"					type="ASCII"			count="Any"></Artist>	<Copyright 					tagid="33432"	tagname="Copyright holder"								type="ASCII" 			count="Any"></Copyright>		<!-- A. Tags Relating to Version -->	<ExifVersion				tagid="36864"	tagname="Exif version"									type="UNDEFINED"		count="4">				</ExifVersion>	<FlashpixVersion			tagid="40960"	tagname="Supported Flashpix version"					type="UNDEFINED"		count="4">				</FlashpixVersion>		<!-- B. Tag Relating to Image Data Characteristics -->	<ColorSpace					tagid="40961"	tagname="Color space information"						type="SHORT"			count="1">				</ColorSpace>					<!-- C. Tags Relating to Image Configuration -->	<ComponentsConfiguration	tagid="37121"	tagname="Meaning of each component"						type="UNDEFINED"		count="4">				</ComponentsConfiguration>	<CompressedBitsPerPixel		tagid="37122"	tagname="Image compression mode"						type="RATIONAL"			count="1">				</CompressedBitsPerPixel>		<PixelXDimension		   	tagid="40962"	tagname="Valid image width"								type="SHORT | LONG"		count="1">				</PixelXDimension>		<PixelYDimension		   	tagid="40963"	tagname="Valid image height"							type="SHORT | LONG"		count="1">				</PixelYDimension>	   			<!-- D. Tags Relating to User Information -->	<MakerNote			    	tagid="37500"	tagname="Manufacturer notes"							type="UNDEFINED"		count="Any">			</MakerNote>			    			<UserComment			   	tagid="37510"	tagname="User comments"									type="UNDEFINED"		count="Any">			</UserComment>		   			<!-- E. Tag Relating to Related File Information -->	<RelatedSoundFile			tagid="40964"	tagname="Related audio file"							type="ASCII"			count="13">			    </RelatedSoundFile>		<!-- F. Tags Relating to Date and Time -->	<DateTimeOriginal			tagid="36867"	tagname="Date and time of original data generation"		type="ASCII"			count="20">			    </DateTimeOriginal>				<DateTimeDigitized			tagid="36868"	tagname="Date and time of digital data generation"		type="ASCII"			count="20">			    </DateTimeDigitized>				<SubSecTime					tagid="37520"	tagname="DateTime subseconds"							type="ASCII"			count="Any">			</SubSecTime>						<SubSecTimeOriginal			tagid="37521"	tagname="DateTimeOriginal subseconds"					type="ASCII"			count="Any">			</SubSecTimeOriginal>	<SubSecTimeDigitized		tagid="37522"	tagname="DateTimeDigitized subseconds"					type="ASCII"			count="Any">			</SubSecTimeDigitized>			<!-- G. Tags Relating to Picture-Taking Conditions -->	<ExposureTime		    	tagid="33434"	tagname="Exposure time"									type="RATIONAL" 		count="1">				</ExposureTime>   		<FNumber				   	tagid="33437"	tagname="F number"										type="RATIONAL"			count="1">				</FNumber>		   		<ExposureProgram		   	tagid="34850"	tagname="Exposure program"								type="SHORT"			count="1">				</ExposureProgram>	<SpectralSensitivity	   	tagid="34852"	tagname="Spectral sensitivity"							type="ASCII"			count="Any">			</SpectralSensitivity>	<ISOSpeedRatings		   	tagid="34855"	tagname="ISO speed rating"								type="SHORT"			count="Any">			</ISOSpeedRatings>	   		<OECF				    	tagid="34856"	tagname="Optoelectric conversion factor"				type="UNDEFINED"		count="Any">			</OECF>	    		<ShutterSpeedValue			tagid="37377"	tagname="Shutter speed"									type="SRATIONAL"		count="1">				</ShutterSpeedValue>	<ApertureValue				tagid="37378"	tagname="Aperture"										type="RATIONAL"			count="1">				</ApertureValue>			<BrightnessValue			tagid="37379"	tagname="Brightness"									type="SRATIONAL"		count="1">				</BrightnessValue>	<ExposureBiasValue	    	tagid="37380"	tagname="Exposure bias"									type="SRATIONAL"		count="1">				</ExposureBiasValue>	<MaxApertureValue	    	tagid="37381"	tagname="Maximum lens aperture"							type="RATIONAL"			count="1">				</MaxApertureValue>    		<SubjectDistance			tagid="37382"	tagname="Subject distance"								type="RATIONAL"			count="1">				</SubjectDistance>	<MeteringMode				tagid="37383"	tagname="Metering mode"									type="SHORT"			count="1">				</MeteringMode>	<LightSource				tagid="37384"	tagname="Light source"									type="SHORT"			count="1">				</LightSource>	<Flash						tagid="37385"  	tagname="Flash"									  	  	type="SHORT"		  	count="1">				</Flash>	<FocalLength				tagid="37386"	tagname="Lens focal length"								type="RATIONAL"			count="1">				</FocalLength>	<SubjectArea				tagid="37396"	tagname="Subject area"   								type="SHORT"			count="2 | 3 | 4">		</SubjectArea>	<FlashEnergy				tagid="41483"	tagname="Flash energy"									type="RATIONAL"			count="1">				</FlashEnergy>	<SpatialFrequencyResponse	tagid="41484"	tagname="Spatial frequency response"					type="UNDEFINED"		count="Any">			</SpatialFrequencyResponse>	<FocalPlaneXResolution		tagid="41486"	tagname="Focal plane X resolution"						type="RATIONAL"			count="1">				</FocalPlaneXResolution>	<FocalPlaneYResolution		tagid="41487"	tagname="Focal plane Y resolution"						type="RATIONAL"			count="1">				</FocalPlaneYResolution>	<FocalPlaneResolutionUnit	tagid="41488"	tagname="Focal plane resolution unit"					type="SHORT"			count="1">				</FocalPlaneResolutionUnit>	<SubjectLocation			tagid="41492"	tagname="Subject location"								type="SHORT"			count="2">				</SubjectLocation>	<ExposureIndex				tagid="41493"	tagname="Exposure index"								type="RATIONAL"			count="1">				</ExposureIndex>	<SensingMethod				tagid="41495"	tagname="Sensing method"								type="SHORT"			count="1">				</SensingMethod>	<FileSource					tagid="41728"	tagname="File source"									type="UNDEFINED"		count="1">				</FileSource>	<SceneType					tagid="41729"	tagname="Scene type"									type="UNDEFINED"		count="1">				</SceneType>	<CFAPattern					tagid="41730"	tagname="CFA pattern"									type="UNDEFINED"		count="Any">			</CFAPattern>	<CustomRendered				tagid="41985"	tagname="Custom image processing"						type="SHORT"			count="1">				</CustomRendered>	<ExposureMode				tagid="41986"	tagname="Exposure mode"									type="SHORT"			count="1">				</ExposureMode>	<WhiteBalance				tagid="41987"	tagname="White balance"									type="SHORT"			count="1">				</WhiteBalance>	<DigitalZoomRatio			tagid="41988"	tagname="Digital zoom ratio"							type="RATIONAL"			count="1">				</DigitalZoomRatio>	<FocalLengthIn35mmFilm		tagid="41989"	tagname="Focal length in 35 mm film"					type="SHORT"			count="1">				</FocalLengthIn35mmFilm>	<SceneCaptureType			tagid="41990"	tagname="Scene capture type"							type="SHORT"			count="1">				</SceneCaptureType>	<GainControl				tagid="41991"	tagname="Gain control"									type="RATIONAL"			count="1">				</GainControl>	<Contrast					tagid="41992"	tagname="Contrast"										type="SHORT"			count="1">				</Contrast>	<Saturation					tagid="41993"	tagname="Saturation"									type="SHORT"			count="1">				</Saturation>	<Sharpness					tagid="41994"	tagname="Sharpness"										type="SHORT"			count="1">				</Sharpness>	<DeviceSettingDescription	tagid="41995"	tagname="Device settings description"         			type="UNDEFINED"		count="Any">			</DeviceSettingDescription>	<SubjectDistanceRange	    tagid="41996"	tagname="Subject distance range"						type="SHORT"			count="1">				</SubjectDistanceRange>	<!-- H. Other Tags -->	<ImageUniqueID				tagid="42016"	tagname="Unique image ID"								type="ASCII"			count="33">				</ImageUniqueID></AVSImageRaw3EXIFGenerator>